thompyson/__init__.py
thompyson/rational/__init__.py
thompyson/rational/dyadic.py
thompyson/tree_pair/__init__.py
thompyson/tree_pair/tree_pair.py
thompyson-1.0.0.dist-info/LICENSE
thompyson-1.0.0.dist-info/METADATA
thompyson-1.0.0.dist-info/WHEEL
thompyson-1.0.0.dist-info/top_level.txt
thompyson-1.0.0.dist-info/RECORD
