Metadata-Version: 2.1
Name: thompyson
Version: 1.0.0
Summary: Utility for computations in R J Thompson's groups F and T.
Home-page: https://github.com/WilliamAngus/thompyson
Author: William Angus
Author-email: william@ngus.co.uk
License: UNKNOWN
Project-URL: Bug Tracker, https://github.com/WilliamAngus/thompyson/issues
Platform: UNKNOWN
Classifier: Programming Language :: Python :: 3
Classifier: License :: OSI Approved :: The Unlicense (Unlicense)
Classifier: Operating System :: OS Independent
Requires-Python: >=3.6
License-File: LICENSE
